{
  "missingUsername": {
    "username": "",
    "password": "fake_password",
    "errorMessage": "Epic sadface: Username is required"
  },
  "missingPassword": {
    "username": "fake_username",
    "password": "",
    "errorMessage": "Epic sadface: Password is required"
  },
  "lockedOut": {
    "username": "locked_out_user",
    "password": "secret_sauce",
    "errorMessage": "Epic sadface: Sorry, this user has been locked out."
  },
  "nonExistingUser": {
    "username": "im_fake_user",
    "password": "im_fake_password",
    "errorMessage": "Epic sadface: Username and password do not match any user in this service"
  }
}